abrevvprint/__init__.py
abrevvprint/core.py
abrevvprint-0.1.0.dist-info/METADATA
abrevvprint-0.1.0.dist-info/WHEEL
abrevvprint-0.1.0.dist-info/top_level.txt
abrevvprint-0.1.0.dist-info/RECORD
