Metadata-Version: 2.4
Name: abrevvprint
Version: 0.1.0
Summary: This module does: 'p' to print, 'pf' to formated print and 'pe' to prefix 'error'
Author-email: KsDev <contatoksdev@tutamail.com>
License: MIT
Requires-Python: >=3.7
